pyrinter/__init__.py
pyrinter/document.py
pyrinter/printers/__init__.py
pyrinter/printers/abs_printer.py
pyrinter/printers/sphinx_printer.py
pyrinter/printers/win_printer.py
pyrinter/utils/__init__.py
pyrinter/utils/sphinx_utils.py
pyrinter/utils/win_utils.py
pyrinter-1.0.1.dist-info/LICENSE
pyrinter-1.0.1.dist-info/METADATA
pyrinter-1.0.1.dist-info/WHEEL
pyrinter-1.0.1.dist-info/top_level.txt
pyrinter-1.0.1.dist-info/RECORD
