Metadata-Version: 2.1
Name: pyrinter
Version: 1.0.1
Summary: python printer package
Author: Hod Vaknin
License: MIT
Project-URL: Source, https://github.com/hodvak/py-printer
Classifier: License :: OSI Approved :: MIT License
Classifier: Environment :: Win32 (MS Windows)
Classifier: Operating System :: Microsoft :: Windows
Classifier: Programming Language :: Python :: 3
License-File: LICENSE
Requires-Dist: pywin32 ; platform_system == "Windows"
